{
  "name": "Annika Langvad Series.5 - Workout 5",
  "note": "Today's session continues to focus on developing your endurance and aerobic conditioning which are fundamental attributes for anyone looking to perform.  \n\nWe are going to push ourselves right up to our threshold, by completing 6 efforts, split in to two blocks of 3 efforts (90%, 95% and 100% of our FTP). As the intensity goes up, the volume goes down so this session is definitely manageable and is a nice building block rather than leaving you totally exhausted for tomorrow. (by Annika Langvad)",
  "intervals": [
    {
      "duration": 420,
      "power": 1.0,
      "note": "Warmup interval"
    },
    {
      "duration": 30,
      "power": 1.0944999,
      "note": "SteadyState interval"
    },
    {
      "duration": 180,
      "power": 0.50449997,
      "note": "SteadyState interval"
    },
    {
      "duration": 30,
      "power": 1.0944999,
      "note": "SteadyState interval"
    },
    {
      "duration": 300,
      "power": 0.50449997,
      "note": "SteadyState interval"
    },
    {
      "duration": 420,
      "power": 0.90449995,
      "note": "SteadyState interval"
    },
    {
      "duration": 90,
      "power": 0.50449997,
      "note": "SteadyState interval"
    },
    {
      "duration": 360,
      "power": 0.95449996,
      "note": "SteadyState interval"
    },
    {
      "duration": 90,
      "power": 0.50449997,
      "note": "SteadyState interval"
    },
    {
      "duration": 300,
      "power": 1.0044999,
      "note": "SteadyState interval"
    },
    {
      "duration": 300,
      "power": 0.50449997,
      "note": "SteadyState interval"
    },
    {
      "duration": 420,
      "power": 0.90449995,
      "note": "SteadyState interval"
    },
    {
      "duration": 90,
      "power": 0.50449997,
      "note": "SteadyState interval"
    },
    {
      "duration": 360,
      "power": 0.95449996,
      "note": "SteadyState interval"
    },
    {
      "duration": 90,
      "power": 0.50449997,
      "note": "SteadyState interval"
    },
    {
      "duration": 300,
      "power": 1.0044999,
      "note": "SteadyState interval"
    },
    {
      "duration": 600,
      "power": 0.50449997,
      "note": "SteadyState interval"
    }
  ]
}