{
  "name": "Week 6.2 - 6 Strength Bombs",
  "note": "This workout can be likened to a race with a hard start - a steady middle and a hard finish as we complete 2 blocks of efforts at 110% of FTP (Zone 5 - Vo2 Max), with a 10 minute block of Zone 3 (82% of FTP) in the middle. \n\nWe are going to complete all 6 of the Zone 5 efforts at a low cadence (65rpm) to simulate being stuck on a really steep section, where you are having to navigate around rocks. You will likely produce a fairly erratic pedaling style as your power output varies significantly from pedal stroke to pedal stroke!\n\nYou will notice the second block of efforts is a lot harder, as we will have the first block of efforts already in our legs - plus the 10 minute aerobic effort too.\n (by Matt Rowe)",
  "intervals": [
    {
      "duration": 420,
      "power": 1.0,
      "note": "Warmup interval"
    },
    {
      "duration": 30,
      "power": 1.0944999,
      "note": "SteadyState interval"
    },
    {
      "duration": 180,
      "power": 0.50449997,
      "note": "SteadyState interval"
    },
    {
      "duration": 30,
      "power": 1.0944999,
      "note": "SteadyState interval"
    },
    {
      "duration": 180,
      "power": 0.50449997,
      "note": "SteadyState interval"
    },
    {
      "duration": 150,
      "power": 1.1044999,
      "note": "interval 150sec @ 1.10"
    },
    {
      "duration": 150,
      "power": 0.30450001,
      "note": "recovery 150sec @ 0.30"
    },
    {
      "duration": 150,
      "power": 1.1044999,
      "note": "interval 150sec @ 1.10"
    },
    {
      "duration": 150,
      "power": 0.30450001,
      "note": "recovery 150sec @ 0.30"
    },
    {
      "duration": 150,
      "power": 1.1044999,
      "note": "interval 150sec @ 1.10"
    },
    {
      "duration": 150,
      "power": 0.30450001,
      "note": "recovery 150sec @ 0.30"
    },
    {
      "duration": 600,
      "power": 0.82449996,
      "note": "SteadyState interval"
    },
    {
      "duration": 150,
      "power": 1.1044999,
      "note": "interval 150sec @ 1.10"
    },
    {
      "duration": 150,
      "power": 0.30450001,
      "note": "recovery 150sec @ 0.30"
    },
    {
      "duration": 150,
      "power": 1.1044999,
      "note": "interval 150sec @ 1.10"
    },
    {
      "duration": 150,
      "power": 0.30450001,
      "note": "recovery 150sec @ 0.30"
    },
    {
      "duration": 150,
      "power": 1.1044999,
      "note": "interval 150sec @ 1.10"
    },
    {
      "duration": 150,
      "power": 0.30450001,
      "note": "recovery 150sec @ 0.30"
    },
    {
      "duration": 360,
      "power": 0.40450001,
      "note": "SteadyState interval"
    }
  ]
}