{
  "name": "Lionel Sanders' Red Day Workout",
  "note": "Lionel Sanders says 'A Red day likely means that I didn't sleep very much or the quality of the sleep was quite low. On these days, I try to not cancel my workout which is why I like to do roller riding. The reason I don't cancel is doing something that is progressing you as an athlete, and you can do successfully, allows you to not put any unnecessary stress into the body on that day. This in turn let's you make sure you get to bed at a decent time and get a good quality sleep to set yourself up for success next day, for the interval work you potentially missed on the red day.' (by Shayne Gaffney)",
  "intervals": [
    {
      "duration": 600,
      "power": 1.0,
      "note": "Warmup interval"
    },
    {
      "duration": 1500,
      "power": 0.5,
      "note": "Free ride"
    },
    {
      "duration": 300,
      "power": 1.0,
      "note": "Cooldown interval"
    }
  ]
}