{
  "name": "Manic Moments",
  "note": "This workout includes segments beginning with 3-minutes in duration decreasing to :20 seconds in duration. The challenge is while the duration decreases the intensity will increase throughout working between 70-120% of your FTP. Once you hit the peak intensity, it's time to come back down in intensity and build back the duration. There will be plenty of pit stops along the way allowing for recovery as well as an opportunity to continue hydrating. (by Kristin Armstrong)",
  "intervals": [
    {
      "duration": 30,
      "power": 0.35,
      "note": "SteadyState interval"
    },
    {
      "duration": 30,
      "power": 0.4,
      "note": "SteadyState interval"
    },
    {
      "duration": 30,
      "power": 0.45,
      "note": "SteadyState interval"
    },
    {
      "duration": 30,
      "power": 0.5,
      "note": "SteadyState interval"
    },
    {
      "duration": 45,
      "power": 0.55,
      "note": "SteadyState interval"
    },
    {
      "duration": 45,
      "power": 0.6,
      "note": "SteadyState interval"
    },
    {
      "duration": 45,
      "power": 0.65,
      "note": "SteadyState interval"
    },
    {
      "duration": 45,
      "power": 0.7,
      "note": "SteadyState interval"
    },
    {
      "duration": 90,
      "power": 0.55,
      "note": "SteadyState interval"
    },
    {
      "duration": 180,
      "power": 0.7,
      "note": "interval 180sec @ 0.70"
    },
    {
      "duration": 45,
      "power": 0.55,
      "note": "recovery 45sec @ 0.55"
    },
    {
      "duration": 120,
      "power": 0.8,
      "note": "interval 120sec @ 0.80"
    },
    {
      "duration": 45,
      "power": 0.55,
      "note": "recovery 45sec @ 0.55"
    },
    {
      "duration": 60,
      "power": 0.9,
      "note": "interval 60sec @ 0.90"
    },
    {
      "duration": 45,
      "power": 0.55,
      "note": "recovery 45sec @ 0.55"
    },
    {
      "duration": 45,
      "power": 1.0,
      "note": "interval 45sec @ 1.00"
    },
    {
      "duration": 45,
      "power": 0.55,
      "note": "recovery 45sec @ 0.55"
    },
    {
      "duration": 30,
      "power": 1.1,
      "note": "interval 30sec @ 1.10"
    },
    {
      "duration": 45,
      "power": 0.55,
      "note": "recovery 45sec @ 0.55"
    },
    {
      "duration": 20,
      "power": 1.2,
      "note": "interval 20sec @ 1.20"
    },
    {
      "duration": 45,
      "power": 0.55,
      "note": "recovery 45sec @ 0.55"
    },
    {
      "duration": 20,
      "power": 1.2,
      "note": "interval 20sec @ 1.20"
    },
    {
      "duration": 45,
      "power": 0.55,
      "note": "recovery 45sec @ 0.55"
    },
    {
      "duration": 30,
      "power": 1.1,
      "note": "interval 30sec @ 1.10"
    },
    {
      "duration": 45,
      "power": 0.55,
      "note": "recovery 45sec @ 0.55"
    },
    {
      "duration": 45,
      "power": 1.0,
      "note": "interval 45sec @ 1.00"
    },
    {
      "duration": 45,
      "power": 0.55,
      "note": "recovery 45sec @ 0.55"
    },
    {
      "duration": 60,
      "power": 0.9,
      "note": "interval 60sec @ 0.90"
    },
    {
      "duration": 45,
      "power": 0.55,
      "note": "recovery 45sec @ 0.55"
    },
    {
      "duration": 120,
      "power": 0.8,
      "note": "interval 120sec @ 0.80"
    },
    {
      "duration": 45,
      "power": 0.55,
      "note": "recovery 45sec @ 0.55"
    },
    {
      "duration": 180,
      "power": 0.7,
      "note": "interval 180sec @ 0.70"
    },
    {
      "duration": 45,
      "power": 0.55,
      "note": "recovery 45sec @ 0.55"
    },
    {
      "duration": 45,
      "power": 0.6,
      "note": "SteadyState interval"
    },
    {
      "duration": 45,
      "power": 0.55,
      "note": "SteadyState interval"
    },
    {
      "duration": 50,
      "power": 0.5,
      "note": "SteadyState interval"
    },
    {
      "duration": 60,
      "power": 0.45,
      "note": "SteadyState interval"
    },
    {
      "duration": 60,
      "power": 0.4,
      "note": "SteadyState interval"
    }
  ]
}